poetry_pypirc/__init__.py
poetry_pypirc/main.py
poetry_pypirc-0.1.2.dist-info/entry_points.txt
poetry_pypirc-0.1.2.dist-info/WHEEL
poetry_pypirc-0.1.2.dist-info/METADATA
poetry_pypirc-0.1.2.dist-info/RECORD
